TemperatureConverter/__init__.py
TemperatureConverterByAdityaBill-0.1.dist-info/LICENSE.txt
TemperatureConverterByAdityaBill-0.1.dist-info/METADATA
TemperatureConverterByAdityaBill-0.1.dist-info/WHEEL
TemperatureConverterByAdityaBill-0.1.dist-info/top_level.txt
TemperatureConverterByAdityaBill-0.1.dist-info/RECORD
