Metadata-Version: 2.1
Name: TemperatureConverterByAdityaBill
Version: 0.1
Summary: This python package is used to convert temperture values in different measurement scales.
Author: Aditya Bikram Arandhara
Author-email: adityabikrambill@gmail.com
License: UNKNOWN
Platform: UNKNOWN
Classifier: Programming Language :: Python :: 3
Classifier: License :: OSI Approved :: MIT License
Classifier: Operating System :: OS Independent
License-File: LICENSE.txt
